dupdict_mod.py
dupdict_mod-1.1.1.dist-info/METADATA
dupdict_mod-1.1.1.dist-info/WHEEL
dupdict_mod-1.1.1.dist-info/top_level.txt
dupdict_mod-1.1.1.dist-info/RECORD
