Metadata-Version: 2.1
Name: dupdict-mod
Version: 1.1.1
Summary: Pure Python dictionary wrapper that allows duplicates
Home-page: http://stromberg.dnsalias.org/~strombrg/dupdict_mod/
Author: Daniel Richard Stromberg
Author-email: strombrg@gmail.com
License: Apache v2
Keywords: dictionary duplicate keys
Platform: Cross platform
Classifier: Development Status :: 5 - Production/Stable
Classifier: Intended Audience :: Developers
Classifier: Programming Language :: Python :: 3
